mul_umn/__init__.py
mul_umn/addition_umn.py
mul_umn-0.0.1.dist-info/LICENSE
mul_umn-0.0.1.dist-info/METADATA
mul_umn-0.0.1.dist-info/WHEEL
mul_umn-0.0.1.dist-info/top_level.txt
mul_umn-0.0.1.dist-info/RECORD
